recogym/__init__.py
recogym/bench_agents.py
recogym/competition.py
recogym/constants.py
recogym/evaluate_agent.py
recogym/agents/__init__.py
recogym/agents/abstract.py
recogym/agents/bandit_count.py
recogym/agents/bandit_mf.py
recogym/agents/bayesian_poly.py
recogym/agents/bayesian_poly_vb.py
recogym/agents/epsilon_greedy.py
recogym/agents/logreg_ips.py
recogym/agents/logreg_poly.py
recogym/agents/nn_ips.py
recogym/agents/organic_count.py
recogym/agents/organic_mf.py
recogym/agents/organic_user_count.py
recogym/agents/pytorch_mlr.py
recogym/agents/random_agent.py
recogym/envs/__init__.py
recogym/envs/abstract.py
recogym/envs/configuration.py
recogym/envs/context.py
recogym/envs/observation.py
recogym/envs/reco_env_v0.py
recogym/envs/reco_env_v1.py
recogym/envs/session.py
recogym/envs/features/__init__.py
recogym/envs/features/time/__init__.py
recogym/envs/features/time/default_time_generator.py
recogym/envs/features/time/normal_time_generator.py
recogym/envs/features/time/time_generator.py
recogym-0.1.3.0.dist-info/LICENSE
recogym-0.1.3.0.dist-info/METADATA
recogym-0.1.3.0.dist-info/WHEEL
recogym-0.1.3.0.dist-info/top_level.txt
recogym-0.1.3.0.dist-info/RECORD
