Metadata-Version: 2.1
Name: recogym
Version: 0.1.3.0
Summary: Open-AI gym reinforcement learning environment for recommendation
Home-page: https://github.com/criteo-research/reco-gym
Author: Criteo AI Lab
License: Apache License
Platform: UNKNOWN
Classifier: License :: OSI Approved :: Apache Software License
Classifier: Programming Language :: Python :: 3
Classifier: Programming Language :: Python :: 3.6
Requires-Dist: absl-py
Requires-Dist: pandas
Requires-Dist: matplotlib
Requires-Dist: simplegeneric
Requires-Dist: gym
Requires-Dist: torch
Requires-Dist: tensorflow
Requires-Dist: numba
Requires-Dist: tqdm
Requires-Dist: datetime
Requires-Dist: jupyter
Requires-Dist: scipy
Requires-Dist: numpy
Requires-Dist: scikit-learn
